{
  "id": "1214",
  "filename": "1214_strava_activities_to_twitter",
  "description": "Triggers when a new activity is created on Strava and automatically tweets the distance and activity name to X (formerly Twitter).",
  "content": {
    "id": "95",
    "name": "Receive updates when a new activity gets created and tweet about it",
    "nodes": [
      {
        "name": "Strava Trigger",
        "type": "n8n-nodes-base.stravaTrigger",
        "position": [
          710,
          220
        ],
        "webhookId": "5ad7a644-4005-4118-a27e-7112bd0035a5",
        "parameters": {
          "event": "create",
          "object": "activity",
          "options": {}
        },
        "credentials": {
          "stravaOAuth2Api": "strava"
        },
        "typeVersion": 1
      },
      {
        "name": "Twitter",
        "type": "n8n-nodes-base.twitter",
        "position": [
          910,
          220
        ],
        "parameters": {
          "text": "=I ran {{$node[\"Strava Trigger\"].json[\"object_data\"][\"distance\"]}} meters and completed my {{$node[\"Strava Trigger\"].json[\"object_data\"][\"name\"]}}!",
          "additionalFields": {}
        },
        "credentials": {
          "twitterOAuth1Api": "twitter-Harshil"
        },
        "typeVersion": 1
      }
    ],
    "active": false,
    "settings": {},
    "connections": {
      "Strava Trigger": {
        "main": [
          [
            {
              "node": "Twitter",
              "type": "main",
              "index": 0
            }
          ]
        ]
      }
    }
  },
  "title": "Automate tweets for new Strava activities",
  "nodes_count": 2,
  "created_at": "2025-06-14T17:34:01.150895Z",
  "updated_at": "2025-06-14T17:34:01.150895Z",
  "categories": [
    "Marketing",
    "Productivity"
  ],
  "services": [
    "Strava",
    "X (Formerly Twitter)"
  ],
  "difficulty": "Beginner",
  "triggers": [
    "New Strava Event"
  ],
  "actions": [],
  "setup_requirements": [
    "Strava Account",
    "X (Formerly Twitter) API Key"
  ],
  "workflow_complexity": 2,
  "external_integrations_count": 2
}